valve_gfx_ci/salad/__init__.py
valve_gfx_ci/salad/app.py
valve_gfx_ci/salad/console.py
valve_gfx_ci/salad/logger.py
valve_gfx_ci/salad/salad.py
valve_gfx_ci/salad/tcpserver.py
valve_gfx_ci/salad/tests/__init__.py
valve_gfx_ci/salad/tests/test_console.py
valve_gfx_ci/salad/tests/test_salad.py
valve_gfx_ci_salad-0.0.2.dist-info/licenses/LICENSE
valve_gfx_ci_salad-0.0.2.dist-info/METADATA
valve_gfx_ci_salad-0.0.2.dist-info/WHEEL
valve_gfx_ci_salad-0.0.2.dist-info/entry_points.txt
valve_gfx_ci_salad-0.0.2.dist-info/top_level.txt
valve_gfx_ci_salad-0.0.2.dist-info/RECORD
