Metadata-Version: 2.4
Name: valve_gfx_ci.salad
Version: 0.0.2
Summary: Valve GFX CI's serial multiplexer
Home-page: https://gitlab.freedesktop.org/gfx-ci/ci-tron/-/tree/main/salad
Author: Martin Roukala
Author-email: martin.roukala@mupuf.org
Project-URL: Bug Tracker, https://gitlab.freedesktop.org/gfx-ci/ci-tron/issues
Classifier: Programming Language :: Python :: 3
Classifier: License :: OSI Approved :: MIT License
Classifier: Operating System :: OS Independent
Requires-Python: >=3.6
License-File: LICENSE
Requires-Dist: Flask<3,>=2.2
Requires-Dist: pyserial==3.5
Requires-Dist: waitress<3,>=2.1.2
Dynamic: license-file
